CrashResolver/__init__.py
CrashResolver/base_parser.py
CrashResolver/config.py
CrashResolver/database_csv.py
CrashResolver/downloader.py
CrashResolver/setup.py
CrashResolver/util.py
CrashResolver/android/crash_parser.py
CrashResolver/android/log_parser.py
CrashResolver/android/main.py
CrashResolver/assets/log.yaml
CrashResolver/assets/settings.ini
CrashResolver/ios/crash_parser.py
CrashResolver/ios/main.py
CrashResolver/test/android_filter.py
CrashResolver/test/android_user_stat.py
crashresolver-1.0.0.dist-info/LICENSE
crashresolver-1.0.0.dist-info/WHEEL
crashresolver-1.0.0.dist-info/METADATA
crashresolver-1.0.0.dist-info/RECORD
