Metadata-Version: 2.1
Name: CrashResolver
Version: 1.0.0
Summary: CrashResolver tries to manage (fetch, symbolicate, gather statistics) multiple crash reports.
Author-email: cosmore <icosmore@gmail.com>
Classifier: License :: OSI Approved :: MIT License
Requires-Dist: requests>=2.28.0
Requires-Dist: PyYAML>=6.0
Project-URL: Documentation, https://github.com/beyonddoor/CrashResolver/
Project-URL: Source, https://github.com/beyonddoor/CrashResolver/
